{
  "guard_id": "bccf0d3172",
  "generation": 3260,
  "model": "MiniMax-M2.7",
  "prompt_hash": "f658a92f",
  "code": "def guard(features: dict, prediction: str) -> str:\n    \"\"\"Multi-indicator confirmation guard requiring 2+ signals to agree.\"\"\"\n    if prediction == \"skip\":\n        return prediction\n    \n    signals_aligned = 0\n    \n    # RSI confirmation\n    if prediction == \"long\" and features.get(\"rsi_14\", 50) > 50:\n        signals_aligned += 1\n    elif prediction == \"short\" and features.get(\"rsi_14\", 50) < 50:\n        signals_aligned += 1\n    \n    # 2h RSI wider context confirmation\n    if prediction == \"long\" and features.get(\"rsi_2h\", 50) > 50:\n        signals_aligned += 1\n    elif prediction == \"short\" and features.get(\"rsi_2h\", 50) < 50:\n        signals_aligned += 1\n    \n    # VWAP deviation confirmation\n    if prediction == \"long\" and features.get(\"vwap_deviation\", 0) > 0:\n        signals_aligned += 1\n    elif prediction == \"short\" and features.get(\"vwap_deviation\", 0) < 0:\n        signals_aligned += 1\n    \n    # Bollinger Band position confirmation\n    if prediction == \"long\" and features.get(\"bb_pct_b\", 0.5) > 0.5:\n        signals_aligned += 1\n    elif prediction == \"short\" and features.get(\"bb_pct_b\", 0.5) < 0.5:\n        signals_aligned += 1\n    \n    # Stochastic confirmation\n    if prediction == \"long\" and features.get(\"stoch_k\", 50) > 50:\n        signals_aligned += 1\n    elif prediction == \"short\" and features.get(\"stoch_k\", 50) < 50:\n        signals_aligned += 1\n    \n    # OBV slope confirmation\n    if prediction == \"long\" and features.get(\"obv_slope\", 0) > 0:\n        signals_aligned += 1\n    elif prediction == \"short\" and features.get(\"obv_slope\", 0) < 0:\n        signals_aligned += 1\n    \n    # MACD histogram confirmation\n    if prediction == \"long\" and features.get(\"macd_histogram\", 0) > 0:\n        signals_aligned += 1\n    elif prediction == \"short\" and features.get(\"macd_histogram\", 0) < 0:\n        signals_aligned += 1\n    \n    return prediction if signals_aligned >= 2 else \"skip\"",
  "file_path": "C:\\Users\\USER\\Desktop\\domain-chip-trading-crypto-evolution\\generated_guards\\guard_bccf0d3172.py"
}