{
  "guard_id": "d59f0288c8",
  "generation": 3340,
  "model": "MiniMax-M2.7",
  "prompt_hash": "5ea0a140",
  "code": "def guard(features: dict, prediction: str) -> str:\n    \"\"\"Guard function filtering trades based on stochastic crossover quality.\"\"\"\n    stoch_k = features.get('stoch_k', 50)\n    stoch_d = features.get('stoch_d', 50)\n    bb_pct_b = features.get('bb_pct_b', 0.5)\n    vwap_dev = features.get('vwap_deviation', 0)\n    rsi_2h = features.get('rsi_2h', 50)\n\n    if prediction == 'long':\n        if stoch_k <= stoch_d:\n            return \"skip\"\n        if stoch_k - stoch_d < 5:\n            return \"skip\"\n        if stoch_k > 80 or stoch_k < 20:\n            return \"skip\"\n        if bb_pct_b > 0.9 or vwap_dev < 0:\n            return \"skip\"\n        if rsi_2h < 45:\n            return \"skip\"\n\n    elif prediction == 'short':\n        if stoch_k >= stoch_d:\n            return \"skip\"\n        if stoch_d - stoch_k < 5:\n            return \"skip\"\n        if stoch_k < 20 or stoch_k > 80:\n            return \"skip\"\n        if bb_pct_b < 0.1 or vwap_dev > 0:\n            return \"skip\"\n        if rsi_2h > 55:\n            return \"skip\"\n\n    return prediction",
  "file_path": "C:\\Users\\USER\\Desktop\\domain-chip-trading-crypto-evolution\\generated_guards\\guard_d59f0288c8.py"
}