{
  "guard_id": "a493cd2b2b",
  "generation": 85,
  "model": "MiniMax-M2.7",
  "prompt_hash": "a8c001e0",
  "code": "def guard(features: dict, prediction: str) -> str:\n    # Skip if high volume but small range - potential manipulation or fakeout\n    if features.get('volume_ratio', 1) > 2.0 and features.get('range_pct', 0.5) < 0.5:\n        return \"skip\"\n    \n    # Skip long signals when RSI oversold but EMA still declining\n    if prediction == \"long\" and features.get('rsi_14', 50) < 40 and features.get('ema_slope', 0) < 0:\n        return \"skip\"\n    \n    # Skip short signals when RSI overbought but EMA still rising\n    if prediction == \"short\" and features.get('rsi_14', 50) > 60 and features.get('ema_slope', 0) > 0:\n        return \"skip\"\n    \n    return prediction",
  "file_path": "C:\\Users\\USER\\Desktop\\domain-chip-trading-crypto-evolution\\generated_guards\\guard_a493cd2b2b.py"
}